mvsma/__init__.py
mvsma/modrinth_api.py
mvsma-1.0.2.dist-info/METADATA
mvsma-1.0.2.dist-info/WHEEL
mvsma-1.0.2.dist-info/licenses/LICENSE
mvsma-1.0.2.dist-info/RECORD
