Metadata-Version: 2.1
Name: mvsma
Version: 1.0.2
Summary: Super simple modrinth api wrapper for python
Project-URL: Github, https://github.com/mhamsterr/mvsma
Author: mhamster
License-File: LICENSE
Classifier: License :: OSI Approved :: MIT License
Classifier: Operating System :: OS Independent
Classifier: Programming Language :: Python :: 3
Requires-Python: >=3.7
